delulify/__init__.py
delulify/__main__.py
delulify/formatter.py
delulify/interceptor.py
delulify/vibes.py
delulify-1.0.2.dist-info/METADATA
delulify-1.0.2.dist-info/WHEEL
delulify-1.0.2.dist-info/entry_points.txt
delulify-1.0.2.dist-info/top_level.txt
delulify-1.0.2.dist-info/RECORD
