Metadata-Version: 2.4
Name: delulify
Version: 1.0.2
Summary: A Python CLI wrapper with emotionally supportive or roasting error messages for crashed scripts.
Home-page: https://github.com/VaishJadhavVJ/delulify.git
Author: Vaishnavi Jadhav
Author-email: sonapjadhav05@gmail.com
Classifier: Programming Language :: Python :: 3
Classifier: License :: OSI Approved :: MIT License
Classifier: Operating System :: OS Independent
Requires-Python: >=3.7
Dynamic: author
Dynamic: author-email
Dynamic: classifier
Dynamic: description
Dynamic: description-content-type
Dynamic: home-page
Dynamic: requires-python
Dynamic: summary
